{
  "custom": "Mond",
  "readout.pattern-bodyname": "{0} mass",
  "units.kg": "kg",
  "sun": "Sonne",
  "my.solar.system": "\"Mein\" Sonnensystem",
  "object.size.actual-size": "realistisch",
  "mass-2": "m2",
  "units.earth.masses": "Erdmassen",
  "mass-1": "m1",
  "planet.control.title": "Planet",
  "module.force-laws.name": "Kraftgesetze",
  "body.name.earth": "Erde",
  "object.size.cartoon": "Cartoon",
  "planet": "Planet",
  "units.light-minutes": "Lichtminuten",
  "sun.planet.controls": "Einstellungen",
  "object.size": "Objektgröße",
  "related.sims": "Ähnliche Simulationen",
  "units": "Einheiten",
  "module.sun-planet-system.name": "Sonnensystem",
  "force-description-pattern-target_source_value": "Kraft auf {0} von {1} = {2} N",
  "units.kilometers": "Kilometer",
  "gravity-force-lab.name": "Schwerkraftlabor",
  "units.meters": "m"
}